main.py
setup.py
fedlearnre.egg-info/PKG-INFO
fedlearnre.egg-info/SOURCES.txt
fedlearnre.egg-info/dependency_links.txt
fedlearnre.egg-info/requires.txt
fedlearnre.egg-info/top_level.txt